pystatkit/__init__.py
pystatkit/core.py
pystatkit-0.1.0.dist-info/METADATA
pystatkit-0.1.0.dist-info/WHEEL
pystatkit-0.1.0.dist-info/top_level.txt
pystatkit-0.1.0.dist-info/RECORD
