Metadata-Version: 2.4
Name: pystatkit
Version: 0.1.0
Summary: Basic statistics functions
Author: PyLib Contributors
License: MIT
Keywords: utilities
Classifier: Development Status :: 3 - Alpha
Classifier: Intended Audience :: Developers
Classifier: License :: OSI Approved :: MIT License
Classifier: Programming Language :: Python :: 3
Requires-Python: >=3.8
